{
    "configurations": [
        {
            "name": "Linux",
            "includePath": [
                "${workspaceFolder}/**",
                "/usr/include/boost/accumulators/framework",
                "/usr/bin/",
                "/path/",
                "/usr/include/llvm-c-14",
                "/usr/include/llvm-14"
            ],
            "defines": [],
            "compilerPath": "/usr/bin/g++-11",
            "cStandard": "c17",
            "cppStandard": "c++17",
            "intelliSenseMode": "linux-clang-x64",
            "browse": {
                "databaseFilename": ""
            }
        }
    ],
    "version": 4
}